BaselineRemoval.py
BaselineRemoval-0.1.6.dist-info/LICENSE
BaselineRemoval-0.1.6.dist-info/METADATA
BaselineRemoval-0.1.6.dist-info/WHEEL
BaselineRemoval-0.1.6.dist-info/top_level.txt
BaselineRemoval-0.1.6.dist-info/RECORD
