Metadata-Version: 2.1
Name: BaselineRemoval
Version: 0.1.6
Summary: Perform baseline removal, baseline correction and baseline substraction for raman spectra using Modpoly, ImodPoly and Zhang fit. Returns baseline-subtracted spectrum
Home-page: https://github.com/StatguyUser/BaselineRemoval
Author: StatguyUser
License: UNKNOWN
Download-URL: https://github.com/StatguyUser/BaselineRemoval.git
Platform: UNKNOWN
Requires-Dist: numpy
Requires-Dist: scikit-learn
Requires-Dist: scipy
